zensvi/__init__.py
zensvi/cv/__init__.py
zensvi/cv/classification/__init__.py
zensvi/cv/classification/base.py
zensvi/cv/classification/glare.py
zensvi/cv/classification/lighting.py
zensvi/cv/classification/panorama.py
zensvi/cv/classification/perception.py
zensvi/cv/classification/places365.py
zensvi/cv/classification/platform.py
zensvi/cv/classification/quality.py
zensvi/cv/classification/reflection.py
zensvi/cv/classification/utils/IO_places365.txt
zensvi/cv/classification/utils/Model_01.py
zensvi/cv/classification/utils/W_sceneattribute_wideresnet18.npy
zensvi/cv/classification/utils/__init__.py
zensvi/cv/classification/utils/categories_places365.txt
zensvi/cv/classification/utils/global_streetscapes.py
zensvi/cv/classification/utils/labels_sunattribute.txt
zensvi/cv/classification/utils/place_pulse.py
zensvi/cv/classification/utils/wideresnet.py
zensvi/cv/classification/utils/wideresnet18_places365.pth.tar
zensvi/cv/classification/view_direction.py
zensvi/cv/classification/weather.py
zensvi/cv/depth_estimation/DepthAnythingV2/DA-2K.md
zensvi/cv/depth_estimation/DepthAnythingV2/LICENSE
zensvi/cv/depth_estimation/DepthAnythingV2/README.md
zensvi/cv/depth_estimation/DepthAnythingV2/__init__.py
zensvi/cv/depth_estimation/DepthAnythingV2/assets/DA-2K.png
zensvi/cv/depth_estimation/DepthAnythingV2/assets/examples/demo01.jpg
zensvi/cv/depth_estimation/DepthAnythingV2/assets/examples/demo02.jpg
zensvi/cv/depth_estimation/DepthAnythingV2/assets/examples/demo03.jpg
zensvi/cv/depth_estimation/DepthAnythingV2/assets/examples/demo04.jpg
zensvi/cv/depth_estimation/DepthAnythingV2/assets/examples/demo05.jpg
zensvi/cv/depth_estimation/DepthAnythingV2/assets/examples/demo06.jpg
zensvi/cv/depth_estimation/DepthAnythingV2/assets/examples/demo07.jpg
zensvi/cv/depth_estimation/DepthAnythingV2/assets/examples/demo08.jpg
zensvi/cv/depth_estimation/DepthAnythingV2/assets/examples/demo09.jpg
zensvi/cv/depth_estimation/DepthAnythingV2/assets/examples/demo10.jpg
zensvi-1.4.0.dist-info/LICENSE
zensvi-1.4.0.dist-info/METADATA
zensvi-1.4.0.dist-info/WHEEL
zensvi-1.4.0.dist-info/RECORD
