Metadata-Version: 2.3
Name: zensvi
Version: 1.4.0
Summary: This package handles downloading, cleaning, analyzing street view imagery in a one-stop and zen manner.
License: MIT
Author: koito19960406
Requires-Python: >=3.9,<3.13
Classifier: License :: OSI Approved :: MIT License
Classifier: Programming Language :: Python :: 3
Classifier: Programming Language :: Python :: 3.9
Classifier: Programming Language :: Python :: 3.10
Classifier: Programming Language :: Python :: 3.11
Classifier: Programming Language :: Python :: 3.12
Requires-Dist: Pillow (>=10.0.0)
Requires-Dist: Pygments (>=2.9.0,<3.0.0)
Requires-Dist: Shapely (>=2.0.0)
Requires-Dist: addict (>=2.4.0,<3.0.0)
Requires-Dist: aiohttp (>=3.9.5,<4.0.0)
Requires-Dist: astral (>=3.2,<4.0)
Requires-Dist: attrs (>=21.2.0,<22.0.0)
Requires-Dist: click (>=8.0.1,<9.0.0)
Requires-Dist: click-plugins (>=1.1.1,<2.0.0)
Requires-Dist: cligj (>=0.7.2,<0.8.0)
Requires-Dist: contextily (>=1.6.0,<2.0.0)
Requires-Dist: docutils (>=0.16)
Requires-Dist: faiss-cpu (>=1.9.0,<2.0.0)
Requires-Dist: geojson (>=2.5.0,<3.0.0)
Requires-Dist: geopandas (>=0.10.0)
Requires-Dist: gradio (==4.29.0)
Requires-Dist: gradio-imageslider (>=0.0.20,<0.0.21)
Requires-Dist: groundingdino-py (>=0.4.0,<0.5.0)
Requires-Dist: h3 (>=3.7.7,<4.0.0)
Requires-Dist: haversine (>=2.3.1,<3.0.0)
Requires-Dist: huggingface_hub (>=0.30.0,<0.31.0)
Requires-Dist: img2vec-pytorch (>=1.0.1,<2.0.0)
Requires-Dist: lightning (>=2.2.3,<3.0.0)
Requires-Dist: mapbox-vector-tile (>=2.0.0,<3.0.0)
Requires-Dist: mercantile (>=1.2.1,<2.0.0)
Requires-Dist: munch (>=2.5.0,<3.0.0)
Requires-Dist: networkx (>=3.1,<4.0)
Requires-Dist: numpy
Requires-Dist: open3d (>=0.19.0,<0.20.0)
Requires-Dist: opencv-python (>=4.5.3)
Requires-Dist: osmnx (>=1.1.1,<2.0.0)
Requires-Dist: pandas
Requires-Dist: polars-lts-cpu (>=0.20.23,<0.21.0)
Requires-Dist: psutil (>=5.8.0,<6.0.0)
Requires-Dist: pyarrow (>=16.0.0,<17.0.0)
Requires-Dist: python-dotenv (>=0.19.0,<0.20.0)
Requires-Dist: requests (>=2.26.0,<3.0.0)
Requires-Dist: requests-toolbelt (>=0.9.1)
Requires-Dist: scikit-learn (>=1.5.2,<2.0.0)
Requires-Dist: scipy (>=1.7,<2.0)
Requires-Dist: seaborn (>=0.13.2,<0.14.0)
Requires-Dist: setuptools (>=64.0.3)
Requires-Dist: streetlevel (>=0,<1)
Requires-Dist: tenacity (>=9.0.0,<10.0.0)
Requires-Dist: timezonefinder (>=6.5.0,<7.0.0)
Requires-Dist: torch (>=2.3)
Requires-Dist: torchvision
Requires-Dist: tqdm (>=4.61.1,<5.0.0)
Requires-Dist: transformers (>=4.10.2,<5.0.0)
Requires-Dist: turfpy (>=0.0.7,<0.0.8)
Requires-Dist: vt2geojson (>=0.2.1,<0.3.0)
